hadith/__init__.py
hadith/base.py
hadith/data/Maliks_Muwatta.csv.gz
hadith/data/Musnad_Ahmad_ibn_Hanbal.csv.gz
hadith/data/Sahih_Bukhari.csv.gz
hadith/data/Sahih_Muslim.csv.gz
hadith/data/Sunan_Abu_Dawud.csv.gz
hadith/data/Sunan_Ibn_Maja.csv.gz
hadith/data/Sunan_al-Nasai.csv.gz
hadith/data/Sunan_al_Darami.csv.gz
hadith/data/Sunan_al_Tirmidhi.csv.gz
hadith-0.0.2a1.dist-info/METADATA
hadith-0.0.2a1.dist-info/WHEEL
hadith-0.0.2a1.dist-info/top_level.txt
hadith-0.0.2a1.dist-info/RECORD
