Metadata-Version: 2.1
Name: hadith
Version: 0.0.2a1
Summary: Helps hadith scholars with quantitative research
Home-page: https://github.com/Umma1/hadith/
Author: Umma Open Source
Author-email: umma.opensource@gmail.com
License: UNKNOWN
Platform: UNKNOWN
Classifier: Development Status :: 3 - Alpha
Classifier: Programming Language :: Python :: 3
Classifier: License :: OSI Approved :: MIT License
Classifier: Operating System :: OS Independent
Requires-Python: >=3.6
Requires-Dist: pandas
Requires-Dist: pyyaml
